Metadata-Version: 1.1
Name: mlpipeline-1
Version: 0.0.7
Summary: An AutoML library
Home-page: UNKNOWN
Author: Debjyoti Banerjee
Author-email: debjyoti.banerjee1994@gmail.com
License: MIT
Keywords: AutoML
Platform: UNKNOWN
Classifier: Development Status :: 5 - Production/Stable
Classifier: Intended Audience :: Developers
Classifier: Programming Language :: Python :: 3
Classifier: Operating System :: Unix
Classifier: Operating System :: MacOS :: MacOS X
Classifier: Operating System :: Microsoft :: Windows
